setup.py
pyams/__init__.py
pyams/vn_diagram.py
pyams.egg-info/PKG-INFO
pyams.egg-info/SOURCES.txt
pyams.egg-info/dependency_links.txt
pyams.egg-info/not-zip-safe
pyams.egg-info/top_level.txt