Metadata-Version: 1.1
Name: pyams
Version: 1.0.0.dev1
Summary: Python Aerospace Mechanics & Structures
Home-page: https://github.com/schang1146/pyams
Author: team.pyams
Author-email: team.pyams@gmail.com
License: MIT
Keywords: aerospace engineering development
Platform: UNKNOWN
Classifier: Development Status :: 3 - Alpha
Classifier: License :: OSI Approved :: MIT License
Classifier: Intended Audience :: Science/Research
Classifier: Topic :: Scientific/Engineering
Classifier: Programming Language :: Python :: 3
